onepiecepredictor/MultiModelsClassifier.py
onepiecepredictor/MultiModelsPredictor.py
onepiecepredictor/MultiModelsRegression.py
onepiecepredictor/OnePieceClassifier.py
onepiecepredictor/OnePiecePredictor2.py
onepiecepredictor/OnePieceRegression.py
onepiecepredictor/__init__.py
onepiecepredictor-1.2.dist-info/LICENSE.txt
onepiecepredictor-1.2.dist-info/METADATA
onepiecepredictor-1.2.dist-info/WHEEL
onepiecepredictor-1.2.dist-info/top_level.txt
onepiecepredictor-1.2.dist-info/RECORD
